{
  "titre": "Adoption et usages actuels de l’IA dans les PME françaises en 2025\n\n### Sources vérifiées\n\n**Source 1** : DFM.fr – Article  \n- URL : https://dfm.fr/articles/etat-des-lieux-ia-pme-france/  \n- Date : 22/05/2025  \n- Fiabilité : 8/10 (site spécialisé en veille technologique et numérique, données récentes)  \n- Extraits clés :  \n  * \"Deux PME françaises sur trois utilisent déjà l'IA, mais dans des usages basiques.\"  \n  * \"L’IA progresse plus vite dans les jeunes entreprises.\"  \n  * \"Les secteurs à forte densité informationnelle creusent l’écart.\"  \n  * \"Les cas d’usage dans les TPE/PME françaises : automatiser ce qu’on fait… sans aller plus loin.\"  \n  * \"La vitesse d’adoption est remarquable pour une technologie si récente.\"  \n- Données factuelles :  \n  * 66 % des PME françaises utilisent l’IA en 2025, principalement pour automatiser des tâches simples.  \n  * Adoption plus rapide chez les entreprises jeunes et dans les secteurs à forte information.\n\n**Source 2** : Bpifrance Le Lab – Étude  \n- URL : https://lelab.bpifrance.fr/Etudes/les-entreprises-francaises-et-l-ia-l-aube-d-une-revolution  \n- Date : 04/06/2025  \n- Fiabilité : 9/10 (étude officielle Bpifrance, large panel de dirigeants)  \n- Extraits clés :  \n  * \"58 % des dirigeants considèrent que l’IA est un enjeu de survie à moyen terme.\"  \n  * \"43 % des dirigeants de PME-ETI ont déjà adopté une stratégie IA.\"  \n  * \"73 % des projets IA sont impulsés par le dirigeant.\"  \n  * \"L’IA dynamiserait la croissance économique de la France d’au moins 1,3 point de PIB par an d’ici 2034.\"  \n  * \"Les PME et ETI produisent 49 % de la valeur ajoutée française.\"  \n- Données factuelles :  \n  * 1209 dirigeants interrogés, 4 profils identifiés (Innovateurs, Bloqués, Sceptiques, Expérimentateurs).  \n  * Adoption IA deux fois plus lente en France que chez les voisins allemands et américains.\n\n**Source 3** : L’Usine Nouvelle – Article  \n- URL : https://www.usinenouvelle.com/editorial/les-eti-et-pme-francaises-conscientes-de-l-importance-de-l-ia-ont-du-mal-a-passer-le-cap.N2233238  \n- Date : 04/06/2025  \n- Fiabilité : 8/10 (média économique reconnu)  \n- Extraits clés :  \n  * \"Seulement 32 % des PME et ETI utilisent des solutions IA avancées.\"  \n  * \"Les dirigeants sont conscients de l’importance de l’IA mais peinent à franchir le cap.\"  \n  * \"Les freins principaux sont le manque de compétences et la complexité des projets.\"  \n  * \"L’IA est perçue comme un levier de compétitivité mais reste sous-exploitée.\"  \n  * \"Les ETI sont plus avancées que les PME dans l’intégration de l’IA.\"  \n- Données factuelles :  \n  * 32 % d’adoption avancée contre 66 % d’usages basiques.  \n  * Freins identifiés : compétences (45 %), coûts (30 %), complexité (25 %).\n\n### Synthèse et angles\n\n- **Convergences** : Forte adoption basique de l’IA (66 %), conscience de l’enjeu stratégique (58 %), impulsion par les dirigeants (73 %), freins liés aux compétences et complexité, importance économique majeure des PME/ETI (49 % VA).  \n- **Divergences** : Différences dans le niveau d’adoption avancée (32 % vs usages basiques), rythme d’adoption plus lent en France que dans d’autres pays.  \n- **Angle Prizm recommandé** : Accompagner les PME/ETI dans le passage de l’usage basique à une stratégie IA structurée, avec focus sur formation et gestion du changement.  \n- **Score global** : 8.5/10",
  "dateCreation": "2025-08-15T09:59:59.457Z",
  "scoreQualite": 0.95,
  "sources": [
    {
      "nom": "DFM.fr",
      "type": "Article",
      "url": "https://dfm.fr/articles/etat-des-lieux-ia-pme-france/",
      "date": "22/05/2025",
      "fiabilite": 8,
      "extraits": [
        "Deux PME françaises sur trois utilisent déjà l'IA, mais dans des usages basiques.",
        "L’IA progresse plus vite dans les jeunes entreprises.",
        "Les secteurs à forte densité informationnelle creusent l’écart.",
        "Les cas d’usage dans les TPE/PME françaises : automatiser ce qu’on fait… sans aller plus loin.",
        "La vitesse d’adoption est remarquable pour une technologie si récente."
      ]
    },
    {
      "nom": "Bpifrance Le Lab",
      "type": "Étude",
      "url": "https://lelab.bpifrance.fr/Etudes/les-entreprises-francaises-et-l-ia-l-aube-d-une-revolution",
      "date": "04/06/2025",
      "fiabilite": 9,
      "extraits": [
        "58 % des dirigeants considèrent que l’IA est un enjeu de survie à moyen terme.",
        "43 % des dirigeants de PME-ETI ont déjà adopté une stratégie IA.",
        "73 % des projets IA sont impulsés par le dirigeant.",
        "L’IA dynamiserait la croissance économique de la France d’au moins 1,3 point de PIB par an d’ici 2034.",
        "Les PME et ETI produisent 49 % de la valeur ajoutée française."
      ]
    },
    {
      "nom": "L’Usine Nouvelle",
      "type": "Article",
      "url": "https://www.usinenouvelle.com/editorial/les-eti-et-pme-francaises-conscientes-de-l-importance-de-l-ia-ont-du-mal-a-passer-le-cap.N2233238",
      "date": "04/06/2025",
      "fiabilite": 8,
      "extraits": [
        "Seulement 32 % des PME et ETI utilisent des solutions IA avancées.",
        "Les dirigeants sont conscients de l’importance de l’IA mais peinent à franchir le cap.",
        "Les freins principaux sont le manque de compétences et la complexité des projets.",
        "L’IA est perçue comme un levier de compétitivité mais reste sous-exploitée.",
        "Les ETI sont plus avancées que les PME dans l’intégration de l’IA."
      ]
    }
  ],
  "synthese": {
    "convergences": "Forte adoption basique de l’IA (66 %), conscience de l’enjeu stratégique (58 %), impulsion par les dirigeants (73 %), freins liés aux compétences et complexité, importance économique majeure des PME/ETI (49 % VA).",
    "divergences": "Différences dans le niveau d’adoption avancée (32 % vs usages basiques), rythme d’adoption plus lent en France que dans d’autres pays.",
    "anglePrizm": "Accompagner les PME/ETI dans le passage de l’usage basique à une stratégie IA structurée, avec focus sur formation et gestion du changement.",
    "scoreGlobal": 0
  }
}